{
  "1e": {
    "1AN": {
      "1AN10-1": "fdfd3",
      "1AN11": "d9fd1",
      "1AN14-4": "e1845",
      "1AN14-5": "58718",
      "1AN14-6": "29311"
    },
    "1E1": {
      "1E10": "f4ca9",
      "1E11-1": "37608",
      "1E11-2": "4e906",
      "1E11-3": "dc18b",
      "1E11-4": "f812e",
      "1E11-5": "c8fcd",
      "1E11": "b0404",
      "1E12-1": "60393",
      "1E12": "92cd4",
      "1E13": "cf8d9",
      "1E14": "0ea25",
      "1E15": "01648",
      "1E16": "5bae7"
    },
    "1F1": {
      "1F10": "0a2a1"
    },
    "1G1": {
      "1G10": "6155a",
      "1G11": "aa7e4",
      "1G12": "51278"
    },
    "1N1": {
      "1N10": "3f63f",
      "1N11": "82375"
    },
    "1P1": {
      "1P10": "e2941"
    },
    "1F": {
      "can1F01": "9142a",
      "can1F02": "d77ec",
      "can1F03": "74ab9",
      "can1F04": "8fa0b",
      "can1F05": "17f01",
      "can1F06": "37aaf",
      "can1F07": "acdc4"
    },
    "1G": {
      "can1G01": "79a7e",
      "can1G02": "c5675",
      "can1G03": "462e3"
    },
    "1L": {
      "can1L01": "baf2a",
      "can1L02": "0e28b",
      "can1L03": "a40ba",
      "can1L04": "17928",
      "can1L05": "cfff6",
      "can1L06": "cac7d",
      "can1L07": "e5b51",
      "can1L08": "caf0f"
    },
    "1P": {
      "can1P01": "69f8a"
    },
    "1S": {
      "can1S01": "b7b65",
      "can1S02": "f7a72",
      "can1S03": "89bd3",
      "can1S04": "003a5",
      "can1S05": "f7961",
      "can1S06": "8da71",
      "can1S07": "6f244",
      "can1S08": "45352",
      "can1S09": "f4da9",
      "can1S10": "669c6",
      "can1S11": "43117"
    }
  },
  "2e": {
    "2F1": {
      "2F10-1": "cb99e",
      "2F10-2": "e0e6d",
      "2F10-3": "c7fe0",
      "2F10-4": "04953",
      "2F10-5": "24fa1",
      "2F10-6": "796d2",
      "2F11-1": "53b5f",
      "2F12-1": "428c6"
    },
    "2F2": {
      "2F20-1": "8d56d",
      "2F25-1": "10c25",
      "2F25-2": "75a0f"
    },
    "2F3": {
      "2F31-1": "478de",
      "2F31-2": "9de89",
      "2F31-3": "3abd5",
      "2F32-2": "17439",
      "2F32-3": "33a3c"
    },
    "2G1": {
      "2G10-1": "3823c",
      "2G10-2": "952b2",
      "2G11-1": "6de7e",
      "2G11-2": "9c4e5",
      "2G11-3": "3f57b",
      "2G11-5": "9213d",
      "2G12-1": "7446b",
      "2G12-2": "085c0",
      "2G12-3": "1c579",
      "2G12-4": "80c50"
    },
    "2G2": {
      "2G21-1": "aeb0b",
      "2G22-1": "e01c5",
      "2G23-2": "d7701",
      "2G24-1": "a9b22"
    },
    "2G3": {
      "2G30-1": "57b68",
      "2G30-2": "ad385",
      "2G30-3": "d510f",
      "2G30-4": "fd9ae",
      "2G30-5": "ad8f1",
      "2G33-1": "edc80",
      "2G33-2": "b5585",
      "2G35-7": "5e0ef"
    },
    "2N1": {
      "2N10-1": "5e35b",
      "2N10-2": "c1e7c",
      "2N10-3": "46cc1",
      "2N11-1": "337c6",
      "2N11-2": "9ff4d",
      "2N12-1": "1c7b5",
      "2N12-2": "0802c",
      "2N13-1": "8acbb",
      "2N14-1": "4d6c9",
      "2N15-1": "9fd8f",
      "2N15-2": "50f61"
    },
    "2N2": {
      "2N20-1": "af94e",
      "2N20-2": "c1f21",
      "2N20-3": "99951",
      "2N20-4": "df9de",
      "2N20-5": "384ca",
      "2N20-6": "3bd3e",
      "2N20-7": "f35a2",
      "2N20-8": "cd77e"
    },
    "2N3": {
      "2N30-1": "e9cab",
      "2N30-2": "53a02",
      "2N30-3": "5f7ff",
      "2N30-4": "f4048",
      "2N30-5": "ff71d",
      "2N30-6": "330b0",
      "2N30-7": "96d2e",
      "2N31-0": "628b3",
      "2N31-1": "2e085",
      "2N31-2": "4dd84",
      "2N31-3": "934d5",
      "2N31-4": "ff7a4",
      "2N32-1": "8cc1d",
      "2N32-2": "d4922",
      "2N32-3": "c4741",
      "2N32-4": "b0c36",
      "2N32-5": "850c7",
      "2N32-6": "f52a2",
      "2N32-7": "6fc47"
    },
    "2N4": {
      "2N40-1": "d0192",
      "2N40-2": "55d0e",
      "2N40-3": "35ef5",
      "2N40-4": "28717",
      "2N40-5": "e2dd9",
      "2N40-6": "32d52",
      "2N41-1": "49a7e",
      "2N41-2": "b223a",
      "2N41-3": "90a7c",
      "2N41-4": "d919f",
      "2N41-5": "c11a6",
      "2N41-6": "f2afc",
      "2N41-7": "dd398",
      "2N41-7v2": "5c012"
    },
    "2N5": {
      "2N50-1": "09610",
      "2N50-2": "9ceea",
      "2N50-3": "8ffa8",
      "2N50-4": "eee89",
      "2N51-1": "76739",
      "2N51-2": "52065",
      "2N51-3": "f7bc1",
      "2N51-3v2": "29151",
      "2N51-4": "4845c",
      "2N51-5": "9ecd2",
      "2N52-1": "41584",
      "2N52-2": "10f05",
      "2N52-4": "a73e2"
    },
    "2N6": {
      "2N60-4": "4a12a",
      "2N61-2": "1c650",
      "2N61-4": "cb59e"
    },
    "2S1": {
      "2S10-2": "a4ade",
      "2S11-1": "25c3a",
      "2S11-2": "82d30",
      "2S12-2": "969ef",
      "2S12-3": "d841a"
    },
    "2S2": {
      "2S20-1": "dcf59",
      "2S20-2": "44ef2",
      "2S20-4": "62657"
    },
    "2S3": {
      "2S30-2": "253a3",
      "2S30-3": "27ff5",
      "2S30-4": "7ac25",
      "2S30-5": "2645c"
    },
    "2a": {
      "can2a-2021": "cb54c"
    },
    "2C": {
      "can2C01": "92031",
      "can2C02": "0384f",
      "can2C03": "f9696",
      "can2C04": "54c3e",
      "can2C05": "14124",
      "can2C06": "dd28e",
      "can2C07": "4de73",
      "can2C08": "cf8ef",
      "can2C09": "55c90",
      "can2C10": "1f5ce",
      "can2C11": "cb503",
      "can2C12": "ad93d"
    },
    "2F": {
      "can2F01": "bbe09",
      "can2F02": "0a8af",
      "can2F03": "76e52",
      "can2F04": "05ebd",
      "can2F05": "207cf",
      "can2F06": "6d4d3",
      "can2F07": "1891c",
      "can2F08": "038cf",
      "can2F09": "f36a9",
      "can2F10": "44976",
      "can2F11": "a4d3d",
      "can2F12": "559c1",
      "can2F13": "34a95"
    },
    "2G": {
      "can2G01": "76ff2",
      "can2G02": "00b00",
      "can2G03": "a274d",
      "can2G04": "7afe5",
      "can2G05": "aadd7",
      "can2G06": "a0a47",
      "can2G07": "e9a3f",
      "can2G08": "ee4dd",
      "can2G09": "4b84f",
      "can2G10": "1b4d2",
      "can2G11": "c7f41",
      "can2G12": "1a5e8",
      "can2G13": "87680",
      "can2G14": "e5e19",
      "can2G15": "b9631"
    },
    "2L": {
      "can2L01": "a968f",
      "can2L02": "dee75",
      "can2L03": "0c0e3",
      "can2L04": "a441e",
      "can2L05": "2b941",
      "can2L06": "eff70",
      "can2L07": "9b7b3",
      "can2L08": "6a428"
    },
    "2N": {
      "can2N01": "b90c7",
      "can2N02": "bf024"
    },
    "2P": {
      "can2P01": "d1c8a",
      "can2P02": "a7a15"
    }
  },
  "3e": {
    "3A1": {
      "3A10": "bb2f5",
      "3A11-1": "6775a",
      "3A11-2": "dac86",
      "3A11-3": "23ec0",
      "3A11": "e05b0",
      "3A12-2": "719dc",
      "3A12": "27b4f",
      "3A13": "4ae1e",
      "3A14": "97368"
    },
    "3F1": {
      "3F1-act": "5eb9e",
      "3F10-1": "617f2",
      "3F10-2": "b5d13",
      "3F10": "baf8a",
      "3F12-2": "614d3",
      "3F12-3": "7d819",
      "3F12-4": "c94df",
      "3F12": "cc3ab",
      "3F13-1": "638df",
      "3F13-2": "3aa00",
      "3F13": "75a4e"
    },
    "3F2": {
      "3F21-1": "1ba33",
      "3F21-2": "dcb22",
      "3F21-3": "3161b",
      "3F21": "2dd9b"
    },
    "3G1": {
      "3G10-1": "9bb86",
      "3G10-2": "a1c9d",
      "3G10-3": "38832",
      "3G11": "aaac4",
      "3G12-1": "7d8ae",
      "3G12": "139a9",
      "3G13": "ad332"
    },
    "3G2": {
      "3G20-1": "4dffe",
      "3G20": "32643",
      "3G21": "47097",
      "3G22-1": "a5fe7",
      "3G22": "6958f",
      "3G23": "80ef3"
    },
    "3G3": {
      "3G30-1": "adb4e",
      "3G30": "97981",
      "3G31-1": "281d0",
      "3G31": "dcf66",
      "3G32-0": "f6fce",
      "3G32-1": "33ec3",
      "3G32-2": "1f25f",
      "3G32-3": "be5b7",
      "3G32-4": "2c6d1",
      "3G32-5": "3c36b",
      "3G32": "c4fd7"
    },
    "3G4": {
      "3G40": "9db13",
      "3G42": "271ce",
      "3G43": "1fb84"
    },
    "3I1": {
      "3I1-1": "77e51",
      "3I1": "f2592"
    },
    "3L1": {
      "3L10-1": "e089b",
      "3L10": "475d2",
      "3L11-1": "6063a",
      "3L11-2": "47989",
      "3L11-3": "5030d",
      "3L11-4": "be40a",
      "3L11-5": "1c4cf",
      "3L11-6": "02083",
      "3L11-7": "5198e",
      "3L11": "7347c",
      "3L12-1": "44ee3",
      "3L12": "cad68",
      "3L13-0": "06919",
      "3L13-1": "b486f",
      "3L13-2": "a6832",
      "3L13-3": "914cb",
      "3L13-4": "670c1",
      "3L13": "10589",
      "3L14-1": "d3230",
      "3L14": "4c3d7",
      "3L15-1": "308fb",
      "3L15": "9a6bf"
    },
    "3P1": {
      "3P10-1": "e2dcd",
      "3P10": "d8842"
    },
    "3S1": {
      "3S12": "57e75",
      "3S15": "252c8"
    },
    "3S2": {
      "3S20": "09cbe",
      "3S21": "ebf2a"
    },
    "3a": {
      "can3a-2021": "38550",
      "can3a-2022": "bcf77"
    },
    "3C": {
      "can3C01": "a653c",
      "can3C02": "c88e3",
      "can3C03": "acc3a",
      "can3C04": "4ca03",
      "can3C05": "19f83",
      "can3C06": "bb53c",
      "can3C07": "3a3a9",
      "can3C08": "517d6",
      "can3C09": "953d2",
      "can3C10": "3ca8e",
      "can3C11": "506d7",
      "can3C12": "52bac"
    },
    "3F": {
      "can3F01": "e57f2",
      "can3F02": "1ee1f",
      "can3F03": "bcfb2",
      "can3F04": "0f07d",
      "can3F05": "90afa",
      "can3F06": "0f55f",
      "can3F07": "f906f",
      "can3F08": "42e83",
      "can3F09": "7d792"
    },
    "3G": {
      "can3G01": "98fbf",
      "can3G02": "dd911",
      "can3G03": "6f408",
      "can3G04": "105fc",
      "can3G05": "6306c"
    },
    "3L": {
      "can3L01": "d2ca0",
      "can3L02": "e83a7",
      "can3L03": "9dbfe",
      "can3L04": "36337",
      "can3L05": "bcaa7"
    },
    "3M": {
      "can3M01": "e77a5",
      "can3M02": "2884b"
    },
    "3P": {
      "can3P01": "49845"
    },
    "3S": {
      "can3S01": "80d58",
      "can3S02": "9978a",
      "can3S03": "06f84",
      "can3S04": "3dfd8",
      "can3S05": "bd9fa",
      "can3S06": "a8f23"
    }
  },
  "MG": {
    "MG32": {
      "MG32_3F13": "eedf7"
    }
  },
  "4e": {
    "4A1": {
      "4A10": "e14ea",
      "4A11-0": "0ff38",
      "4A11-1": "c2395",
      "4A11-2": "91c1f",
      "4A12": "4e6de"
    },
    "4C1": {
      "4C10-0": "5d820",
      "4C10-1": "23a21",
      "4C10-2": "ff82f",
      "4C10-3": "abc7d",
      "4C10-4": "b2623",
      "4C10-5": "11852",
      "4C10-6": "e87e9",
      "4C11": "49f09"
    },
    "4C2": {
      "4C20-1": "1f365",
      "4C20-2": "f6683",
      "4C20": "b44f5",
      "4C21-1": "adc7b",
      "4C21": "cb517",
      "4C22-1": "52100",
      "4C22-2": "4d727",
      "4C22": "16824",
      "4C23-1": "96226",
      "4C23": "c3f91",
      "4C24": "3ff29",
      "4C25-0": "6d6ee"
    },
    "4C3": {
      "4C30-1": "17414",
      "4C30-2": "40796",
      "4C30-3": "23ff4",
      "4C30-4": "0592e",
      "4C30": "b5aee",
      "4C32-0": "d99fd",
      "4C32-1": "415f6",
      "4C32-2": "a047c",
      "4C32-3": "64093",
      "4C32": "67a01",
      "4C33-0": "0c70e",
      "4C33-1": "8e019",
      "4C33-3": "c1c9e",
      "4C34": "a411c",
      "4C35": "a90d8",
      "4C36": "e454f"
    },
    "4F1": {
      "4F12": "09464"
    },
    "4G1": {
      "4G10-1": "8aae4",
      "4G10-2": "6ffc0",
      "4G10": "802e6",
      "4G11-1": "98d79",
      "4G11": "0e25e",
      "4G12-1": "b96ed",
      "4G12-2": "1d4d9",
      "4G12": "fcf76",
      "4G15": "e6d2f"
    },
    "4G2": {
      "4G20-1": "2c987",
      "4G20-2": "3e9a3",
      "4G20-4": "ae72e",
      "4G20-5": "50565",
      "4G20-6": "52892",
      "4G20": "a9e6f",
      "4G21": "0772b",
      "4G22": "c9954"
    },
    "4G3": {
      "4G30": "dfc97",
      "4G31": "bec2f"
    },
    "4G4": {
      "4G40-1": "60afe",
      "4G40-2": "7ae4b",
      "4G40": "00d32",
      "4G41": "0f90a"
    },
    "4G5": {
      "4G51": "b1584",
      "4G52": "f6edb",
      "4G53": "8dcd8"
    },
    "4I1": {
      "4I1-2": "14a2d",
      "4I1": "0df00"
    },
    "4L1": {
      "4L10-1": "64caf",
      "4L10-2": "9371e",
      "4L10": "e4d69",
      "4L11": "c5cb7",
      "4L12": "a4780",
      "4L13-0": "cdd93",
      "4L13-1": "77df1",
      "4L13-2": "bf226",
      "4L14-0": "c0c47",
      "4L14-1": "14ce4",
      "4L14-2": "5b1e8",
      "4L15-0": "f5069",
      "4L15-1": "f144d",
      "4L16": "cfee1"
    },
    "4L2": {
      "4L20-0": "f86c9",
      "4L20": "ea5d8"
    },
    "4P1": {
      "4P10-1": "876df",
      "4P10-2": "d2513",
      "4P10": "2af35",
      "4P16": "589a4"
    },
    "4S1": {
      "4S10": "ac7ee",
      "4S11": "0b3e0"
    },
    "4S2": {
      "4S20": "e230a"
    },
    "4a": {
      "can4a-2021": "29431",
      "can4a-2022": "abe28"
    },
    "4C": {
      "can4C01": "33090",
      "can4C02": "a7291",
      "can4C03": "40de0",
      "can4C04": "d7fe2",
      "can4C05": "2a15a",
      "can4C06": "618c9",
      "can4C07": "78cc1",
      "can4C08": "a5f4b",
      "can4C09": "984cc",
      "can4C10": "f8fa6"
    },
    "4G": {
      "can4G01": "76b37",
      "can4G02": "a3f50",
      "can4G03": "e5b26",
      "can4G04": "4b001",
      "can4G05": "45a10",
      "can4G06": "d9f7b",
      "can4G07": "dd3cf",
      "can4G08": "bb367"
    },
    "4L": {
      "can4L01": "096cb",
      "can4L02": "cb6ac",
      "can4L03": "38a7f",
      "can4L04": "93003",
      "can4L05": "f9b45",
      "can4L06": "8a1f9",
      "can4L07": "5ab19",
      "can4L08": "20159"
    },
    "4P": {
      "can4P01": "b5558",
      "can4P02": "a8072",
      "can4P03": "32997",
      "can4P04": "0547a",
      "can4P05": "de24e"
    }
  },
  "5e": {
    "5A1": {
      "5A10": "5aad8",
      "5A11-1": "3023c",
      "5A11-2": "417e3",
      "5A11": "5bd32",
      "5A12-1": "117b8",
      "5A13": "08a90"
    },
    "5C1": {
      "5C11-1": "83ca2",
      "5C11-2": "71014",
      "5C11": "e2e37",
      "5C12-1": "aaaba",
      "5C12": "18490"
    },
    "5G1": {
      "5G10-1": "5ec6a",
      "5G10-2": "1e688",
      "5G10": "37105",
      "5G11-1": "6a07c",
      "5G11-2": "acd6e",
      "5G11-3": "033d9",
      "5G11-4": "75ab9",
      "5G11-5": "49cad",
      "5G11-6": "dda82",
      "5G11": "e1714",
      "5G12-1": "56493",
      "5G12-2": "625fa",
      "5G12-3": "61273",
      "5G12": "f8701",
      "5G13": "a73b7"
    },
    "5G2": {
      "5G20-0": "064bf",
      "5G20-1": "062de",
      "5G20-2": "ed3b3",
      "5G20": "87afc",
      "5G21-1": "5e741",
      "5G22-1": "eb075",
      "5G22": "7b4e4",
      "5G24-1": "a6777",
      "5G24-2": "e62f5"
    },
    "5G3": {
      "5G30-1": "366e2",
      "5G30-2": "c090a",
      "5G30": "2b862",
      "5G31-1": "a053d",
      "5G31": "b26e9"
    },
    "5G4": {
      "5G40-1": "5c0b5",
      "5G40-2": "f28b1",
      "5G40": "a8c2b",
      "5G41": "e1e25",
      "5G42": "18cdd"
    },
    "5G5": {
      "5G51": "905fe"
    },
    "5I1": {
      "5I11": "e610b"
    },
    "5L1": {
      "5L10-1": "45c33",
      "5L10-2": "8eae6",
      "5L10-3": "60222",
      "5L10-4": "1a2d4",
      "5L10": "fe462",
      "5L12-1": "d6b51",
      "5L12-2": "668dc",
      "5L12": "6f1fa",
      "5L13": "9084e",
      "5L14-1": "38d09",
      "5L14-2": "594f0",
      "5L14-3": "1a52f",
      "5L14-4": "ba728",
      "5L14-5": "e4f72",
      "5L14-6": "41f9c",
      "5L14": "47161",
      "5L15": "1f693",
      "5L16": "e28d6"
    },
    "5M1": {
      "5M10": "d45bb"
    },
    "5M2": {
      "5M20": "2cfa4"
    },
    "5N1": {
      "5N10": "01196",
      "5N11-1": "2ff0d",
      "5N11-2": "143b2",
      "5N11-3": "9a9c6",
      "5N11-4": "e71e0",
      "5N110": "f9d3f",
      "5N13-2": "ab32d",
      "5N13": "e3589",
      "5N14-2": "e882b",
      "5N14-3": "9254d",
      "5N14": "648a1",
      "5N15": "5e1b1"
    },
    "5N2": {
      "5N20-0": "b949b",
      "5N20": "b4b7f"
    },
    "5P1": {
      "5P10": "a2bea",
      "5P11-1": "c1a67",
      "5P12": "6a9ee"
    },
    "5R1": {
      "5R10-0": "d57f1",
      "5R10-1": "5b6a0",
      "5R10": "da9a0",
      "5R11-2": "ba507",
      "5R11": "e349e",
      "5R12-2": "edcf1",
      "5R12": "36c99"
    },
    "5R2": {
      "5R20-2": "16749",
      "5R20-3": "267a1",
      "5R20-4": "c0bc5",
      "5R20-5": "91178",
      "5R20": "3362b",
      "5R21": "bf4cf",
      "5R22-2": "ba09f",
      "5R22": "88fc2"
    },
    "5S1": {
      "5S10": "4a43c",
      "5S11": "7d1d6",
      "5S12": "5f6b6",
      "5S13-1": "6ccbf",
      "5S13-2": "1d36a",
      "5S13": "969c4",
      "5S14": "4d3d6"
    },
    "5S2": {
      "5S20": "577a1",
      "5S21-1": "b27ec",
      "5S21": "0bd00",
      "5S22": "dca68"
    },
    "5a": {
      "can5a-2021": "b4e7d",
      "can5a-2022": "991da"
    },
    "5A": {
      "can5A01": "cc377"
    },
    "5C": {
      "can5C01": "27e95",
      "can5C02": "33dc9",
      "can5C03": "15ce3",
      "can5C04": "fc386",
      "can5C05": "7d22b",
      "can5C06": "2d7a3",
      "can5C07": "5688a",
      "can5C08": "34468",
      "can5C09": "dadb7",
      "can5C10": "477a9",
      "can5C11": "266c7",
      "can5C12": "b76e1",
      "can5C13": "691d7",
      "can5C14": "398db",
      "can5C15": "fb881",
      "can5C16": "72eeb",
      "can5C17": "502ea",
      "can5C18": "18ca0",
      "can5C19": "eeb70",
      "can5C20": "17a26",
      "can5C21": "96637"
    },
    "5D": {
      "can5D01": "8c80e",
      "can5D02": "e044b",
      "can5D03": "4ff98"
    },
    "5G": {
      "can5G01": "cf75e",
      "can5G02": "75980",
      "can5G03": "28b48"
    },
    "5L": {
      "can5L01": "d25bb"
    },
    "5N": {
      "can5N01": "a5334",
      "can5N02": "ce02e"
    },
    "5P": {
      "can5P01": "0ef69",
      "can5P02": "51d4a",
      "can5P03": "4d419",
      "can5P04": "35d9d",
      "can5P05": "a23aa",
      "can5P06": "e4476"
    }
  },
  "6e": {
    "6C1": {
      "6C10-1": "1b6f8",
      "6C10-2": "9dfc2",
      "6C10-3": "f4655",
      "6C10-4": "73046",
      "6C10-5": "33f74",
      "6C10": "b8acc",
      "6C11-1": "abc68",
      "6C11-2": "146e5",
      "6C11": "00013",
      "6C12-1": "77250",
      "6C12-3": "cf9e5",
      "6C12-4": "594d1",
      "6C12": "d8c43",
      "6C13": "bbeae"
    },
    "6C2": {
      "6C20": "d5a46",
      "6C21": "965a1",
      "6C22": "39f88",
      "6C23": "f5aa7"
    },
    "6C3": {
      "6C30-0": "4b047",
      "6C30-1": "392f3",
      "6C30-2": "21734",
      "6C30-3": "4f013",
      "6C30-4": "5924b",
      "6C30-5": "8bb79",
      "6C30-6": "f27a7",
      "6C30-7": "22962",
      "6C30-8": "989cf",
      "6C30": "c284d",
      "6C31-2": "e97dc",
      "6C31": "df835",
      "6C32": "b0fe3",
      "6C33": "9f286",
      "6C34": "743e4",
      "6C35": "b8ff8"
    },
    "6D1": {
      "6D10": "8607a",
      "6D101": "4114b",
      "6D11": "f376e",
      "6D12": "5b18a",
      "6D13": "3f61b"
    },
    "6G1": {
      "6G10-1": "28670",
      "6G10-2": "9701d",
      "6G10-3": "458da",
      "6G10": "eaadf",
      "6G11": "3206f",
      "6G12-1": "fdf94",
      "6G12": "8508d",
      "6G14": "3fc53"
    },
    "6G2": {
      "6G20-2": "be32e",
      "6G20": "ba39d",
      "6G21-1": "7d6dc",
      "6G21": "599ed",
      "6G22": "e6c10",
      "6G23-1": "5938a",
      "6G23-2": "ff422",
      "6G23-3": "ee515",
      "6G23-4": "af8d4",
      "6G23-5": "23068",
      "6G23": "e51ab",
      "6G24-1": "ab0d0",
      "6G24-2": "8f81b",
      "6G24-3": "fe362",
      "6G24-4": "1fa69",
      "6G24": "45a28",
      "6G25-1": "56287",
      "6G25-2": "3d315",
      "6G25-3": "5aa57",
      "6G25": "bf207",
      "6G26": "39b38"
    },
    "6G3": {
      "6G32-1": "fedb3",
      "6G33": "99ce3"
    },
    "6G4": {
      "6G41": "aee3b",
      "6G42": "e781e",
      "6G43": "d36f6",
      "6G44": "80a5e"
    },
    "6I1": {
      "6I10": "c50a6",
      "6I11": "31763",
      "6I12": "7564c"
    },
    "6M1": {
      "6M10-1": "36b6b",
      "6M10": "1e817",
      "6M11-1": "1ffe6",
      "6M11-2": "23194",
      "6M11": "9e900",
      "6M12": "c7961"
    },
    "6M2": {
      "6M20": "50ae8",
      "6M21": "83758",
      "6M22-1": "af7d4",
      "6M22-2": "e4368",
      "6M22": "7f4d5",
      "6M23": "3bfc3",
      "6M25": "17dc9"
    },
    "6M3": {
      "6M30-0": "a9b6e",
      "6M30": "0b013",
      "6M31-2": "04df0",
      "6M31": "a22c7"
    },
    "6N1": {
      "6N10-0": "24204",
      "6N10-1": "3644d",
      "6N10-2": "fb7c6",
      "6N10-3": "889d4",
      "6N10-4": "cef09",
      "6N10-5": "ddf61",
      "6N10-6": "171a2",
      "6N10": "a7aa2",
      "6N11-2": "3d3c8",
      "6N11-3": "1ea5c",
      "6N11-4": "20443",
      "6N11": "b3990",
      "6N12-1": "af28a",
      "6N12": "5a8a7",
      "6N13": "b6078",
      "6N14": "4f36f"
    },
    "6N2": {
      "6N20-1": "89447",
      "6N20-2": "e582d",
      "6N20": "16055",
      "6N21": "b2868",
      "6N22-1": "4ab0a",
      "6N22-2": "a4f19",
      "6N22": "9cc78",
      "6N23-0": "1ccc7",
      "6N23-1": "46ac1",
      "6N23-2": "58ee1",
      "6N23-3": "b4ac5",
      "6N23-4": "dc927",
      "6N23-5": "f2a1d",
      "6N23-6": "41b19",
      "6N23-7": "15b26",
      "6N23": "9e30b",
      "6N24-1": "148a0",
      "6N24": "a97a5"
    },
    "6N3": {
      "6N30-1": "30f32",
      "6N30-2": "38e9f",
      "6N30": "294b9",
      "6N31-1": "4225f",
      "6N31-2": "5db2e",
      "6N31-3": "f55ed",
      "6N31-4": "e0373",
      "6N31": "c7c5e",
      "6N32": "c2e21",
      "6N33-0": "a2c84",
      "6N33-1": "f3c0f",
      "6N33-2": "4837a",
      "6N33-3": "5a17b",
      "6N33": "482ca",
      "6N34": "84375"
    },
    "6N4": {
      "6N41-1": "48671",
      "6N41": "f0870",
      "6N43-2": "b3b29",
      "6N43-3": "40014",
      "6N43-4": "87a85",
      "6N43": "38d82"
    },
    "6P1": {
      "6P10": "dadd7",
      "6P11-1": "2cc40",
      "6P11-2": "7e9e9",
      "6P11": "a119e",
      "6P12": "6917c",
      "6P13-1": "c6ed7",
      "6P13": "94bdb",
      "6P14": "c60e5"
    },
    "6S1": {
      "6S10-1": "f3e50",
      "6S10": "cfb88",
      "6S11": "25364"
    },
    "6a": {
      "can6a-2018": "ef907",
      "can6a-2021": "6efce",
      "can6a-2022": "b62d2"
    },
    "6C": {
      "can6C01": "a8065",
      "can6C02": "3922c",
      "can6C03": "6f58c",
      "can6C04": "0d52b",
      "can6C05": "26c93",
      "can6C06": "7d356",
      "can6C07": "a19f9",
      "can6C08": "6f6ee",
      "can6C09": "075b5",
      "can6C10": "5a367",
      "can6C11": "ee5a4",
      "can6C12": "f73d4",
      "can6C13": "92558",
      "can6C14": "b76fb",
      "can6C15": "4526e",
      "can6C16": "2aece",
      "can6C17": "acd3f",
      "can6C18": "dd396",
      "can6C19": "c91e7",
      "can6C20": "6ae7f",
      "can6C21": "84ce4",
      "can6C22": "3a839",
      "can6C23": "64055",
      "can6C24": "ea697",
      "can6C25": "7cfd5",
      "can6C26": "744b2",
      "can6C27": "319e1",
      "can6C28": "4fd9a",
      "can6C29": "c9313",
      "can6C30": "188ad",
      "can6C31": "af1c9"
    },
    "6D": {
      "can6D01": "f2486",
      "can6D02": "5655a",
      "can6D03": "81fef",
      "can6D04": "9fca6"
    },
    "6G": {
      "can6G01": "be3e5",
      "can6G02": "95a11",
      "can6G03": "07b92",
      "can6G04": "5aea4",
      "can6G05": "42b0e",
      "can6G06": "fd770",
      "can6G07": "ef4f1"
    },
    "6I": {
      "can6I01": "af88e"
    },
    "6M": {
      "can6M01": "06202",
      "can6M02": "a3aba",
      "can6M03": "e2557",
      "can6M04": "dfe8d",
      "can6M05": "30dbc",
      "can6M06": "04ea0",
      "can6M07": "62b21",
      "can6M08": "f7300",
      "can6M09": "8d452"
    },
    "6N": {
      "can6N01": "e3724",
      "can6N02": "70f92",
      "can6N03": "868a9",
      "can6N04": "c233d",
      "can6N05": "f3561",
      "can6N06": "a87ce",
      "can6N07": "37af7",
      "can6N08": "367be",
      "can6N09": "37dcd",
      "can6N10": "832ba",
      "can6N11": "1e768",
      "can6N12": "371b9",
      "can6N13": "a7217",
      "can6N14": "230be"
    },
    "6P": {
      "can6P01": "fbef4",
      "can6P02": "52c77",
      "can6P03": "7b5d6",
      "can6P04": "eaa72",
      "can6P05": "38756"
    },
    "6S": {
      "can6S01": "0d05c"
    }
  },
  "c3": {
    "c3C1": {
      "c3C10-1": "cb281",
      "c3C10-2": "f1559",
      "c3C10-3": "4ed1a",
      "c3C10-4": "09331",
      "c3C10": "7b0bd",
      "c3C11": "13f89",
      "c3C12": "1cd21",
      "c3C13-1": "8d18c",
      "c3C13": "2c428"
    },
    "c3C2": {
      "c3C23": "090ed"
    },
    "c3C3": {
      "c3C30": "1f455",
      "c3C31": "6a57e",
      "c3C3CaN": "2bade"
    },
    "c3I1": {
      "c3I11": "dd59f"
    },
    "c3N1": {
      "c3N10": "89469",
      "c3N11": "9a374"
    },
    "c3N2": {
      "c3N20": "d2fc6",
      "c3N22": "fad9c",
      "c3N23": "8b9de"
    },
    "c3N3": {
      "c3N30": "15a65"
    },
    "c3C": {
      "canc3C01": "7a6e8",
      "canc3C02": "ee558",
      "canc3C03": "22320",
      "canc3C04": "3a224",
      "canc3C05": "d5347",
      "canc3C06": "24861"
    },
    "c3D": {
      "canc3D01": "c4426",
      "canc3D02": "540d7",
      "canc3D03": "7dbdb"
    },
    "c3M": {
      "canc3M01": "dded9"
    },
    "c3N": {
      "canc3N01": "5332c",
      "canc3N02": "18600",
      "canc3N03": "48687",
      "canc3N04": "71599",
      "canc3N05": "b2010"
    }
  },
  "Pr": {
    "Pre": {
      "canPredef5-1": "04436",
      "canPredef6-3": "4bced"
    }
  },
  "Ex": {
    "ExC": {
      "canExC01": "00a23",
      "canExC02": "5a989"
    },
    "ExC1": {
      "ExC100": "9cd37"
    }
  },
  "CM": {
    "CM00": {
      "CM000": "de407",
      "CM001": "41332",
      "CM002": "5727a",
      "CM003": "b7a54",
      "CM004": "20616",
      "CM005": "ad417",
      "CM006": "1019b",
      "CM007": "e12a9",
      "CM008": "f9b9a",
      "CM009": "3d187"
    },
    "CM01": {
      "CM010": "fa780",
      "CM011": "26b04",
      "CM012": "35523",
      "CM013": "89b0d",
      "CM014": "c85c7",
      "CM015": "c216f",
      "CM016": "80537",
      "CM017": "2f31d",
      "CM018": "25c88",
      "CM019": "f0a9b"
    },
    "CM02": {
      "CM020": "e0ea6",
      "CM021": "4f7c7"
    }
  },
  "HP": {
    "HPC1": {
      "HPC100": "a7d6f",
      "HPC102": "0e81f"
    }
  },
  "PE": {
    "PEA1": {
      "PEA11-1": "b3f51",
      "PEA11": "5564e",
      "PEA12": "a6a02",
      "PEA13": "f4847"
    },
    "PEG2": {
      "PEG20": "8c119",
      "PEG21": "cb6fa",
      "PEG22": "5146d",
      "PEG23": "1a16a",
      "PEG24": "fa522"
    }
  }
}